{
  "mcpServers": {
    "supabase": {
      "command": "npx",
      "args": ["@supabase/mcp-server"],
      "env": {
        "SUPABASE_URL": "YOUR_SUPABASE_PROJECT_URL",
        "SUPABASE_ANON_KEY": "YOUR_SUPABASE_ANON_KEY"
      }
    },
    "postgres": {
      "command": "npx",
      "args": ["@modelcontextprotocol/server-postgres"],
      "env": {
        "POSTGRES_CONNECTION_STRING": "YOUR_SUPABASE_POSTGRES_CONNECTION_STRING"
      }
    },
    "filesystem": {
      "command": "npx",
      "args": ["@modelcontextprotocol/server-filesystem", "/Users/sandeepramdaz/NeurallEmpire"]
    },
    "web-search": {
      "command": "npx",
      "args": ["@modelcontextprotocol/server-web-search"]
    },
    "brave-search": {
      "command": "npx",
      "args": ["@modelcontextprotocol/server-brave-search"],
      "env": {
        "BRAVE_API_KEY": "YOUR_BRAVE_API_KEY"
      }
    },
    "github": {
      "command": "npx",
      "args": ["@modelcontextprotocol/server-github"],
      "env": {
        "GITHUB_PERSONAL_ACCESS_TOKEN": "YOUR_GITHUB_TOKEN"
      }
    }
  }
}